{
  "operations": {
    "createVpc": {
      "errors": [
        "InvalidParameterValue",
        "MissingParameter",
        "ParseError",
        "VpcLimitExceeded"
      ]
    },
    "deleteVpc": {
      "errors": [
        "DependencyViolation",
        "InvalidVpcID.NotFound",
        "InvalidVpcId.Malformed",
        "MissingParameter",
        "RequestError"
      ]
    },
    "createSubnet": {
      "errors": [
        "InvalidParameterValue",
        "InvalidVpcID.NotFound",
        "MissingParameter",
        "ParseError"
      ]
    },
    "deleteSubnet": {
      "errors": [
        "DependencyViolation",
        "InvalidSubnetID.NotFound",
        "InvalidSubnetId.Malformed",
        "MissingParameter"
      ]
    },
    "createInternetGateway": {
      "errors": [
        "InternetGatewayLimitExceeded",
        "ParseError"
      ]
    },
    "deleteInternetGateway": {
      "errors": [
        "DependencyViolation",
        "InvalidInternetGatewayID.NotFound",
        "InvalidInternetGatewayId.Malformed"
      ]
    },
    "attachInternetGateway": {
      "errors": [
        "InvalidVpcID.NotFound",
        "InvalidInternetGatewayID.NotFound",
        "InvalidInternetGatewayId.Malformed",
        "InvalidVpcId.Malformed"
      ]
    },
    "detachInternetGateway": {
      "errors": [
        "DependencyViolation",
        "Gateway.NotAttached",
        "InvalidInternetGatewayID.NotFound",
        "InvalidInternetGatewayId.Malformed",
        "InvalidVpcId.Malformed"
      ]
    },
    "createRouteTable": {
      "errors": [
        "InvalidVpcID.NotFound",
        "MissingParameter",
        "ParseError"
      ]
    },
    "deleteRouteTable": {
      "errors": [
        "DependencyViolation",
        "InvalidRouteTableID.NotFound",
        "InvalidRouteTableId.Malformed"
      ]
    },
    "createRoute": {
      "errors": [
        "InvalidGatewayID.NotFound",
        "InvalidInstanceID.Malformed",
        "InvalidNetworkInterfaceID.NotFound",
        "InvalidPrefixListID.NotFound",
        "InvalidRouteTableID.NotFound",
        "InvalidRouteTableId.Malformed",
        "InvalidVpcEndpointId.NotFound",
        "MissingParameter"
      ]
    },
    "createNatGateway": {
      "errors": [
        "InvalidElasticIpID.NotFound",
        "InvalidSubnet",
        "InvalidSubnetID.NotFound",
        "MissingParameter",
        "ParseError"
      ]
    },
    "describeVpcs": {
      "errors": [
        "InvalidVpcID.NotFound",
        "ParseError",
        "RequestError"
      ]
    },
    "describeSubnets": {
      "errors": [
        "InvalidSubnetID.NotFound",
        "ParseError"
      ]
    },
    "describeInternetGateways": {
      "errors": [
        "InvalidInternetGatewayID.NotFound",
        "ParseError"
      ]
    },
    "describeRouteTables": {
      "errors": [
        "InvalidRouteTableID.NotFound",
        "ParseError"
      ]
    },
    "deleteSecurityGroup": {
      "errors": [
        "CannotDelete",
        "DependencyViolation",
        "InvalidGroup.NotFound",
        "InvalidGroupId.Malformed",
        "MissingParameter",
        "VPCIdNotSpecified"
      ]
    },
    "createNetworkAcl": {
      "errors": [
        "InvalidVpcID.NotFound",
        "MissingParameter",
        "ParseError"
      ]
    },
    "deleteNetworkAcl": {
      "errors": [
        "DependencyViolation",
        "DryRunOperation",
        "InvalidNetworkAclID.NotFound",
        "InvalidNetworkAclId.Malformed",
        "InvalidParameterValue",
        "MissingParameter"
      ]
    },
    "createVpcPeeringConnection": {
      "errors": [
        "InvalidVpcID.NotFound",
        "InvalidVpcId.Malformed",
        "MissingParameter",
        "ParseError"
      ]
    },
    "acceptVpcPeeringConnection": {
      "errors": [
        "InvalidVpcPeeringConnectionID.NotFound",
        "InvalidVpcPeeringConnectionId.NotFound"
      ]
    },
    "deleteDhcpOptions": {
      "errors": [
        "DependencyViolation",
        "InvalidDhcpOptionID.NotFound",
        "InvalidDhcpOptionsID.NotFound",
        "InvalidDhcpOptionsId.Malformed"
      ]
    },
    "associateDhcpOptions": {
      "errors": [
        "InvalidDhcpOptionsId.Malformed",
        "InvalidVpcID.NotFound",
        "InvalidVpcId.Malformed"
      ]
    },
    "associateRouteTable": {
      "errors": [
        "DryRunOperation",
        "InvalidParameterCombination",
        "InvalidParameterValue",
        "InvalidPublicIpv4PoolID.Malformed",
        "InvalidPublicIpv4PoolID.NotFound",
        "InvalidRouteTableID.NotFound",
        "InvalidSubnetID.NotFound",
        "MissingParameter"
      ]
    },
    "disassociateRouteTable": {
      "errors": [
        "InvalidAssociationID.NotFound",
        "MissingParameter"
      ]
    },
    "describeNatGateways": {
      "errors": [
        "DryRunOperation",
        "FilterLimitExceeded",
        "InvalidParameter",
        "NatGatewayMalformed",
        "NatGatewayNotFound",
        "ParseError"
      ]
    },
    "createVpcEndpoint": {
      "errors": [
        "InvalidParameter",
        "InvalidServiceName",
        "InvalidVpcID.NotFound",
        "InvalidVpcId.NotFound",
        "ParseError"
      ]
    },
    "deleteVpcEndpoints": {
      "errors": [
        "ParseError"
      ]
    },
    "rejectVpcPeeringConnection": {
      "errors": [
        "InvalidVpcPeeringConnectionID.NotFound",
        "InvalidVpcPeeringConnectionId.NotFound",
        "MissingParameter"
      ]
    },
    "deleteVpcPeeringConnection": {
      "errors": [
        "InvalidVpcPeeringConnectionID.NotFound",
        "InvalidVpcPeeringConnectionId.NotFound",
        "MissingParameter"
      ]
    },
    "associateVpcCidrBlock": {
      "errors": [
        "CidrConflict",
        "InvalidParameterCombination",
        "InvalidVpcID.NotFound",
        "InvalidVpcId.Malformed",
        "MissingParameter"
      ]
    },
    "modifySubnetAttribute": {
      "errors": [
        "InvalidSubnetID.NotFound",
        "MissingParameter"
      ]
    },
    "disassociateVpcCidrBlock": {
      "errors": [
        "InvalidVpcCidrBlockAssociationID.NotFound",
        "InvalidVpcCidrBlockAssociationId.Malformed",
        "InvalidVpcCidrBlockAssociationIdError.NotFound",
        "OperationNotPermitted"
      ]
    },
    "authorizeSecurityGroupIngress": {
      "errors": [
        "InvalidGroup.NotFound",
        "InvalidGroupId.Malformed",
        "MissingParameter"
      ]
    },
    "revokeSecurityGroupIngress": {
      "errors": [
        "InvalidGroup.NotFound",
        "InvalidGroupId.Malformed",
        "InvalidPermission.NotFound",
        "MissingParameter",
        "ParseError"
      ]
    },
    "createNetworkInterface": {
      "errors": [
        "InvalidSubnetID.NotFound",
        "MissingParameter",
        "ParseError"
      ]
    },
    "deleteNetworkInterface": {
      "errors": [
        "InvalidNetworkInterface.InUse",
        "InvalidNetworkInterfaceID.NotFound",
        "InvalidNetworkInterfaceId.Malformed",
        "InvalidParameterValue",
        "MissingParameter"
      ]
    },
    "createEgressOnlyInternetGateway": {
      "errors": [
        "InvalidVpcID.NotFound",
        "InvalidVpcId.Malformed",
        "MissingParameter",
        "ParseError"
      ]
    },
    "deleteEgressOnlyInternetGateway": {
      "errors": [
        "DryRunOperation",
        "InvalidGatewayID.NotFound",
        "InvalidEgressOnlyInternetGatewayId.NotFound",
        "MalformedGatewayID.NotFound",
        "MissingParameter"
      ]
    },
    "createVpnGateway": {
      "errors": [
        "MissingParameter",
        "ParseError"
      ]
    },
    "deleteVpnGateway": {
      "errors": [
        "IncorrectState",
        "InvalidVpnGatewayID.NotFound"
      ]
    },
    "attachVpnGateway": {
      "errors": [
        "InvalidVpcID.NotFound",
        "InvalidVpnGatewayID.NotFound"
      ]
    },
    "detachVpnGateway": {
      "errors": [
        "DependencyViolation",
        "IncorrectState",
        "InvalidVpnGatewayID.NotFound",
        "MissingParameter"
      ]
    },
    "createSecurityGroup": {
      "errors": [
        "InvalidGroup.Duplicate",
        "InvalidParameterValue",
        "InvalidVpcID.NotFound",
        "InvalidVpcId.Malformed",
        "MissingParameter",
        "VPCIdNotSpecified"
      ]
    },
    "createDhcpOptions": {
      "errors": [
        "MissingParameter",
        "ParseError"
      ]
    },
    "createNetworkAclEntry": {
      "errors": [
        "InvalidNetworkAclID.NotFound",
        "MissingParameter"
      ]
    },
    "deleteNetworkAclEntry": {
      "errors": [
        "InvalidNetworkAclEntry.NotFound",
        "InvalidNetworkAclID.NotFound",
        "InvalidNetworkAclId.Malformed",
        "MissingParameter"
      ]
    },
    "replaceNetworkAclEntry": {
      "errors": [
        "InvalidNetworkAclID.NotFound",
        "InvalidNetworkAclId.Malformed"
      ]
    },
    "createVpnConnection": {
      "errors": [
        "InvalidCustomerGatewayID.NotFound",
        "InvalidParameterValue",
        "MissingParameter",
        "ParseError"
      ]
    },
    "deleteVpnConnection": {
      "errors": [
        "InvalidVpnConnectionID.NotFound",
        "MissingParameter"
      ]
    },
    "createCustomerGateway": {
      "errors": [
        "MissingParameter",
        "ParseError"
      ]
    },
    "createTransitGatewayVpcAttachment": {
      "errors": [
        "InvalidSubnetID.NotFound",
        "InvalidTransitGatewayID.NotFound",
        "MissingParameter"
      ]
    },
    "describeVpcAttribute": {
      "errors": [
        "InvalidParameterCombination",
        "InvalidVpcID.NotFound"
      ]
    },
    "describeVpnGateways": {
      "errors": [
        "InvalidVpnGatewayID.NotFound",
        "ParseError"
      ]
    },
    "describeCustomerGateways": {
      "errors": [
        "InvalidCustomerGatewayID.NotFound",
        "ParseError"
      ]
    },
    "authorizeSecurityGroupEgress": {
      "errors": [
        "InvalidGroup.NotFound",
        "InvalidGroupId.Malformed",
        "MissingParameter"
      ]
    },
    "revokeSecurityGroupEgress": {
      "errors": [
        "InvalidGroup.NotFound",
        "InvalidGroupId.Malformed",
        "InvalidParameterValue",
        "InvalidPrefixListID.NotFound",
        "InvalidPermission.NotFound",
        "InvalidSecurityGroupRuleId.Malformed",
        "MissingParameter",
        "UnknownParameter"
      ]
    },
    "describeSecurityGroups": {
      "errors": [
        "InvalidGroup.NotFound",
        "InvalidGroupId.Malformed",
        "ParseError",
        "VPCIdNotSpecified"
      ]
    },
    "describeNetworkAcls": {
      "errors": [
        "InvalidNetworkAclID.NotFound",
        "InvalidRouteTableID.NotFound",
        "ParseError"
      ]
    },
    "createCarrierGateway": {
      "errors": [
        "InvalidVpcID.NotFound",
        "InvalidVpcId.Malformed",
        "MissingParameter",
        "ParseError"
      ]
    },
    "deleteCarrierGateway": {
      "errors": [
        "InvalidCarrierGatewayID.Malformed",
        "InvalidCarrierGatewayID.NotFound",
        "MissingParameter"
      ]
    },
    "createFlowLogs": {
      "errors": [
        "InvalidID",
        "InvalidParameterValue",
        "MissingParameter"
      ]
    },
    "deleteFlowLogs": {
      "errors": [
        "InvalidFlowLogId.NotFound"
      ]
    },
    "createManagedPrefixList": {
      "errors": [
        "InvalidParameterValue",
        "ParseError"
      ]
    },
    "describeVpcPeeringConnections": {
      "errors": [
        "InvalidVpcPeeringConnectionID.NotFound",
        "ParseError"
      ]
    },
    "modifyVpcPeeringConnectionOptions": {
      "errors": [
        "InvalidVpcPeeringConnectionID.NotFound",
        "InvalidVpcPeeringConnectionId.NotFound"
      ]
    },
    "describeVpcEndpoints": {
      "errors": [
        "InvalidVpcEndpointId.NotFound",
        "ParseError"
      ]
    },
    "modifyVpcEndpoint": {
      "errors": [
        "InvalidVpcEndpointId.NotFound"
      ]
    },
    "replaceRoute": {
      "errors": [
        "InvalidRouteTableID.NotFound",
        "MissingParameter"
      ]
    },
    "deleteRoute": {
      "errors": [
        "InvalidParameterCombination",
        "InvalidParameterValue",
        "InvalidRoute.NotFound",
        "InvalidRouteTableID.NotFound",
        "InvalidRouteTableId.Malformed",
        "MissingParameter"
      ]
    },
    "describeVpcEndpointServices": {
      "errors": [
        "ParseError"
      ]
    },
    "modifyNetworkInterfaceAttribute": {
      "errors": [
        "InvalidNetworkInterfaceID.NotFound",
        "InvalidNetworkInterfaceId.Malformed",
        "InvalidParameterCombination"
      ]
    },
    "describeNetworkInterfaces": {
      "errors": [
        "InvalidNetworkInterfaceID.NotFound",
        "InvalidNetworkInterfaceId.Malformed",
        "ParseError"
      ]
    },
    "describeManagedPrefixLists": {
      "errors": [
        "InvalidPrefixListID.NotFound",
        "ParseError"
      ]
    },
    "describeTransitGateways": {
      "errors": [
        "InvalidTransitGatewayID.NotFound",
        "ParseError"
      ]
    },
    "describeCarrierGateways": {
      "errors": [
        "InvalidCarrierGatewayID.Malformed",
        "InvalidCarrierGatewayID.NotFound",
        "ParseError"
      ]
    },
    "describeFlowLogs": {
      "errors": [
        "ParseError"
      ]
    },
    "describeTransitGatewayAttachments": {
      "errors": [
        "InvalidTransitGatewayAttachmentID.NotFound",
        "ParseError"
      ]
    },
    "describeVpnConnections": {
      "errors": [
        "InvalidVpnConnectionID.NotFound"
      ]
    },
    "deleteCustomerGateway": {
      "errors": [
        "InvalidCustomerGatewayID.NotFound",
        "InvalidCustomerGatewayId.Malformed",
        "MissingParameter"
      ]
    },
    "modifyVpcAttribute": {
      "errors": [
        "InvalidParameterCombination",
        "InvalidVpcID.NotFound"
      ]
    },
    "replaceRouteTableAssociation": {
      "errors": [
        "InvalidRouteTableAssociationId.Malformed",
        "InvalidRouteTableID.NotFound"
      ]
    },
    "modifyVpcEndpointServiceConfiguration": {
      "errors": [
        "InvalidVpcEndpointServiceId.Malformed",
        "InvalidVpcEndpointServiceId.NotFound"
      ]
    },
    "describeVpcEndpointServiceConfigurations": {
      "errors": [
        "InvalidVpcEndpointServiceId.NotFound"
      ]
    },
    "describeDhcpOptions": {
      "errors": [
        "InvalidDhcpOptionID.NotFound",
        "InvalidParameterValue",
        "ParseError"
      ]
    },
    "describeNetworkInterfaceAttribute": {
      "errors": [
        "InvalidNetworkInterfaceID.NotFound",
        "InvalidNetworkInterfaceId.Malformed",
        "InvalidParameterCombination"
      ]
    },
    "attachNetworkInterface": {
      "errors": [
        "InvalidInstanceID.Malformed",
        "InvalidInstanceID.NotFound",
        "InvalidNetworkInterfaceID.NotFound"
      ]
    },
    "detachNetworkInterface": {
      "errors": [
        "DependencyViolation",
        "InvalidAttachmentID.NotFound",
        "InvalidNetworkInterfaceAttachmentId.Malformed"
      ]
    },
    "assignPrivateIpAddresses": {
      "errors": [
        "InvalidNetworkInterfaceID.NotFound",
        "InvalidNetworkInterfaceId.Malformed",
        "InvalidParameter"
      ]
    },
    "unassignPrivateIpAddresses": {
      "errors": [
        "InvalidNetworkInterfaceID.NotFound",
        "InvalidNetworkInterfaceId.Malformed",
        "MissingParameter"
      ]
    },
    "assignIpv6Addresses": {
      "errors": [
        "InvalidNetworkInterfaceID.NotFound",
        "InvalidParameterCombination"
      ]
    },
    "unassignIpv6Addresses": {
      "errors": [
        "InvalidNetworkInterfaceID.NotFound",
        "InvalidParameterCombination"
      ]
    },
    "associateSubnetCidrBlock": {
      "errors": [
        "InvalidSubnetID.NotFound",
        "MissingParameter"
      ]
    },
    "disassociateSubnetCidrBlock": {
      "errors": [
        "InvalidSubnetCidrBlockAssociationID.NotFound",
        "InvalidSubnetCidrBlockAssociationId.Malformed"
      ]
    },
    "getSecurityGroupsForVpc": {
      "errors": [
        "InvalidVpcId.Malformed",
        "ParseError"
      ]
    },
    "modifyVpcTenancy": {
      "errors": [
        "InvalidVpcID.NotFound",
        "InvalidVpcId.Malformed"
      ]
    },
    "createDefaultSubnet": {
      "errors": [
        "DefaultSubnetAlreadyExistsInAvailabilityZone",
        "MissingParameter"
      ]
    },
    "createDefaultVpc": {
      "errors": [
        "DefaultVpcAlreadyExists"
      ]
    },
    "describeVpcClassicLink": {
      "errors": [
        "InvalidVpcID.NotFound",
        "InvalidVpcId.Malformed"
      ]
    },
    "describeVpcClassicLinkDnsSupport": {
      "errors": [
        "InvalidVpcID.NotFound"
      ]
    },
    "enableVpcClassicLink": {
      "errors": [
        "InvalidVpcID.NotFound",
        "InvalidVpcId.Malformed"
      ]
    },
    "disableVpcClassicLink": {
      "errors": [
        "InvalidVpcID.NotFound",
        "InvalidVpcId.Malformed"
      ]
    },
    "enableVpcClassicLinkDnsSupport": {
      "errors": [
        "InvalidVpcID.NotFound",
        "MissingParameter"
      ]
    },
    "disableVpcClassicLinkDnsSupport": {
      "errors": [
        "InvalidVpcID.NotFound",
        "MissingParameter"
      ]
    },
    "deleteManagedPrefixList": {
      "errors": [
        "InvalidPrefixListID.NotFound",
        "InvalidPrefixListId.Malformed",
        "ParseError"
      ]
    },
    "releaseAddress": {
      "errors": [
        "AuthFailure",
        "DryRunOperation",
        "InvalidAddress.NotFound",
        "InvalidAllocationID.NotFound",
        "InvalidIPAddress.InUse",
        "InvalidParameterCombination",
        "InvalidParameterValue",
        "MissingParameter"
      ]
    },
    "associateAddress": {
      "errors": [
        "AuthFailure",
        "InvalidAllocationID.NotFound",
        "InvalidInstanceID.NotFound",
        "MissingParameter"
      ]
    },
    "disassociateAddress": {
      "errors": [
        "InvalidAssociationID.NotFound",
        "MissingParameter"
      ]
    },
    "describeAddresses": {
      "errors": [
        "InvalidAllocationID.NotFound"
      ]
    },
    "describeEgressOnlyInternetGateways": {
      "errors": [
        "InvalidEgressOnlyInternetGatewayId.Malformed",
        "InvalidEgressOnlyInternetGatewayId.NotFound",
        "ParseError"
      ]
    },
    "describeAddressesAttribute": {
      "errors": [
        "InvalidAllocationID.NotFound"
      ]
    },
    "describeSecurityGroupRules": {
      "errors": [
        "InvalidSecurityGroupRuleId.NotFound"
      ]
    },
    "describeTags": {
      "errors": [
        "ParseError"
      ]
    },
    "deleteTags": {
      "errors": [
        "InvalidID",
        "MissingParameter"
      ]
    },
    "createTags": {
      "errors": [
        "InvalidID",
        "MissingParameter"
      ]
    },
    "describeInstanceAttribute": {
      "errors": [
        "InvalidInstanceID.NotFound",
        "InvalidParameterValue"
      ]
    },
    "modifyInstanceAttribute": {
      "errors": [
        "InvalidInstanceID.NotFound",
        "InvalidParameterValue"
      ]
    },
    "describeSnapshots": {
      "errors": [
        "InvalidSnapshot.NotFound",
        "InvalidUserID.Malformed"
      ]
    },
    "describeVolumes": {
      "errors": [
        "InvalidParameterValue",
        "InvalidVolume.NotFound",
        "ParseError"
      ]
    },
    "deleteSnapshot": {
      "errors": [
        "InvalidParameterValue",
        "InvalidSnapshot.NotFound",
        "InvalidSnapshotID.Malformed"
      ]
    },
    "deleteVolume": {
      "errors": [
        "InvalidParameterValue",
        "InvalidVolume.NotFound"
      ]
    },
    "runInstances": {
      "errors": [
        "InvalidAMIID.Malformed",
        "InvalidAMIID.NotFound",
        "MissingParameter",
        "ParseError"
      ]
    },
    "attachVolume": {
      "errors": [
        "InvalidInstanceID.NotFound",
        "InvalidParameterValue",
        "InvalidVolume.NotFound"
      ]
    },
    "terminateInstances": {
      "errors": [
        "InvalidInstanceID.Malformed",
        "InvalidInstanceID.NotFound",
        "InvalidParameterCombination"
      ]
    },
    "describeInstances": {
      "errors": [
        "InvalidInstanceID.Malformed",
        "InvalidInstanceID.NotFound",
        "ParseError"
      ]
    },
    "detachVolume": {
      "errors": [
        "DependencyViolation",
        "IncorrectState",
        "InvalidParameterValue",
        "InvalidVolume.NotFound"
      ]
    },
    "createSnapshot": {
      "errors": [
        "InvalidParameterValue",
        "InvalidVolume.NotFound",
        "InvalidVolumeID.Malformed"
      ]
    },
    "startInstances": {
      "errors": [
        "InvalidInstanceID.Malformed",
        "InvalidInstanceID.NotFound",
        "InvalidParameterCombination"
      ]
    },
    "stopInstances": {
      "errors": [
        "InvalidInstanceID.Malformed",
        "InvalidInstanceID.NotFound",
        "InvalidParameterCombination"
      ]
    },
    "rebootInstances": {
      "errors": [
        "InvalidInstanceID.Malformed",
        "InvalidInstanceID.NotFound",
        "MissingParameter"
      ]
    },
    "modifyVolume": {
      "errors": [
        "InvalidParameterValue",
        "InvalidVolume.NotFound",
        "InvalidVolumeID.Malformed"
      ]
    },
    "describeImages": {
      "errors": [
        "InvalidAMIID.Malformed",
        "InvalidAMIID.NotFound"
      ]
    },
    "deregisterImage": {
      "errors": [
        "InvalidAMIID.Malformed",
        "InvalidAMIID.NotFound",
        "MissingParameter"
      ]
    },
    "describeKeyPairs": {
      "errors": [
        "InvalidKeyPair.NotFound",
        "InvalidParameterValue"
      ]
    },
    "copySnapshot": {
      "errors": [
        "InvalidParameterValue",
        "InvalidRegion",
        "InvalidSnapshot.NotFound"
      ]
    },
    "describeSnapshotAttribute": {
      "errors": [
        "InvalidParameterValue",
        "InvalidSnapshot.NotFound",
        "MissingParameter"
      ]
    },
    "modifyImageAttribute": {
      "errors": [
        "InvalidAMIID.Malformed",
        "InvalidAMIID.NotFound",
        "InvalidParameterCombination"
      ]
    },
    "createLaunchTemplate": {
      "errors": [
        "MissingParameter"
      ]
    },
    "deleteLaunchTemplate": {
      "errors": [
        "InvalidLaunchTemplateName.NotFoundException",
        "MissingParameter"
      ]
    },
    "describeLaunchTemplates": {
      "errors": [
        "InvalidLaunchTemplateId.Malformed",
        "ParseError"
      ]
    },
    "createTransitGateway": {
      "errors": [
        "ParseError",
        "TransitGatewayLimitExceeded"
      ]
    },
    "describeInstanceStatus": {
      "errors": [
        "InvalidInstanceID.Malformed",
        "InvalidInstanceID.NotFound"
      ]
    },
    "getConsoleOutput": {
      "errors": [
        "InvalidInstanceID.Malformed",
        "InvalidInstanceID.NotFound"
      ]
    },
    "getPasswordData": {
      "errors": [
        "InvalidInstanceID.Malformed",
        "InvalidInstanceID.NotFound"
      ]
    },
    "createImage": {
      "errors": [
        "InvalidInstanceID.NotFound",
        "InvalidParameterValue"
      ]
    },
    "copyImage": {
      "errors": [
        "InvalidAMIID.Malformed",
        "InvalidAMIID.NotFound",
        "InvalidRegion",
        "InvalidRequest"
      ]
    },
    "describeSpotInstanceRequests": {
      "errors": [
        "InvalidSpotInstanceRequestID.Malformed",
        "ParseError"
      ]
    },
    "describeSpotFleetRequests": {
      "errors": [
        "InvalidParameterValue",
        "ParseError"
      ]
    },
    "getManagedPrefixListEntries": {
      "errors": [
        "InvalidPrefixListID.NotFound",
        "InvalidPrefixListId.Malformed",
        "ParseError"
      ]
    },
    "describeAvailabilityZones": {
      "errors": [
        "InvalidParameterValue",
        "ParseError"
      ]
    },
    "deleteTransitGateway": {
      "errors": [
        "IncorrectState",
        "InvalidTransitGatewayID.Malformed",
        "InvalidTransitGatewayID.NotFound",
        "MissingParameter",
        "ParseError"
      ]
    },
    "createTransitGatewayRouteTable": {
      "errors": [
        "IncorrectState",
        "InvalidTransitGatewayID.NotFound",
        "MissingParameter",
        "ParseError"
      ]
    },
    "deleteTransitGatewayRouteTable": {
      "errors": [
        "IncorrectState",
        "InvalidRouteTableID.NotFound",
        "InvalidRouteTableId.Malformed",
        "MissingParameter",
        "ParseError"
      ]
    },
    "modifySnapshotAttribute": {
      "errors": [
        "InvalidParameterCombination",
        "InvalidSnapshot.NotFound"
      ]
    },
    "createKeyPair": {
      "errors": [
        "InvalidKeyPair.Duplicate"
      ]
    },
    "describeTransitGatewayRouteTables": {
      "errors": [
        "InvalidRouteTableID.NotFound",
        "ParseError"
      ]
    },
    "deleteNatGateway": {
      "errors": [
        "DryRunOperation",
        "InvalidParameter",
        "MissingParameter",
        "NatGatewayMalformed",
        "NatGatewayNotFound"
      ]
    },
    "deleteClientVpnEndpoint": {
      "errors": [
        "InvalidClientVpnEndpointId.NotFound"
      ]
    },
    "deleteNetworkInterfacePermission": {
      "errors": [
        "InvalidPermissionID.Malformed",
        "InvalidPermissionID.NotFound",
        "MissingParameter"
      ]
    },
    "createIpam": {
      "errors": [
        "InvalidParameterValue",
        "ParseError",
        "ResourceLimitExceeded"
      ]
    },
    "deleteIpam": {
      "errors": [
        "DependencyViolation",
        "InvalidIpamId.NotFound",
        "MissingParameter"
      ]
    },
    "deleteTransitGatewayVpcAttachment": {
      "errors": [
        "InvalidTransitGatewayAttachmentID.Malformed",
        "InvalidTransitGatewayAttachmentID.NotFound"
      ]
    },
    "createTransitGatewayMulticastDomain": {
      "errors": [
        "IncorrectState",
        "InvalidTransitGatewayID.Malformed",
        "InvalidTransitGatewayID.NotFound",
        "MissingParameter"
      ]
    },
    "createLocalGatewayRouteTable": {
      "errors": [
        "InvalidLocalGatewayID.Malformed",
        "InvalidLocalGatewayID.NotFound",
        "MissingParameter"
      ]
    },
    "createSubnetCidrReservation": {
      "errors": [
        "InvalidParameterValue",
        "InvalidSubnetID.Malformed",
        "MissingParameter"
      ]
    },
    "deleteSubnetCidrReservation": {
      "errors": [
        "InvalidSubnetCidrReservationID.Malformed",
        "InvalidSubnetCidrReservationID.NotFound",
        "MissingParameter"
      ]
    },
    "createTrafficMirrorFilter": {
      "errors": [
        "ParseError"
      ]
    },
    "deleteTrafficMirrorFilter": {
      "errors": [
        "InvalidParameterValue",
        "InvalidTrafficMirrorFilterId.NotFound"
      ]
    },
    "deleteTrafficMirrorTarget": {
      "errors": [
        "InvalidParameterValue",
        "InvalidTrafficMirrorTargetId.NotFound",
        "MissingParameter"
      ]
    },
    "deleteTrafficMirrorSession": {
      "errors": [
        "InvalidParameterValue",
        "InvalidTrafficMirrorSessionId.NotFound",
        "MissingParameter"
      ]
    },
    "createNetworkInsightsPath": {
      "errors": [
        "InvalidParameterValue",
        "MissingParameter"
      ]
    },
    "deleteNetworkInsightsPath": {
      "errors": [
        "InvalidParameterValue",
        "MissingParameter"
      ]
    },
    "deleteNetworkInsightsAccessScope": {
      "errors": [
        "InvalidNetworkInsightsAccessScopeId.NotFound",
        "InvalidParameterValue"
      ]
    },
    "deletePlacementGroup": {
      "errors": [
        "InvalidPlacementGroup.Unknown"
      ]
    },
    "createCoipPool": {
      "errors": [
        "InvalidLocalGatewayRouteTableID.Malformed",
        "InvalidLocalGatewayRouteTableID.NotFound",
        "MissingParameter"
      ]
    },
    "deleteCoipPool": {
      "errors": [
        "InvalidIpv4PoolCoipId.Malformed",
        "InvalidParameterValue",
        "MissingParameter"
      ]
    },
    "createClientVpnEndpoint": {
      "errors": [
        "MissingParameter"
      ]
    },
    "createVerifiedAccessInstance": {
      "errors": [
        "ParseError",
        "VerifiedAccessInstanceLimitExceeded"
      ]
    },
    "deleteVerifiedAccessInstance": {
      "errors": [
        "InvalidVerifiedAccessInstanceId.NotFound"
      ]
    },
    "createVerifiedAccessGroup": {
      "errors": [
        "InvalidParameterValue",
        "InvalidVerifiedAccessInstanceId.NotFound",
        "MissingParameter"
      ]
    },
    "deleteVerifiedAccessGroup": {
      "errors": [
        "InvalidVerifiedAccessGroupId.NotFound",
        "MissingParameter"
      ]
    },
    "deleteVerifiedAccessEndpoint": {
      "errors": [
        "InvalidParameterValue",
        "InvalidVerifiedAccessEndpointId.NotFound",
        "MissingParameter"
      ]
    },
    "createVerifiedAccessTrustProvider": {
      "errors": [
        "MissingParameter"
      ]
    },
    "deleteVerifiedAccessTrustProvider": {
      "errors": [
        "InvalidVerifiedAccessTrustProviderId.NotFound"
      ]
    },
    "createIpamPool": {
      "errors": [
        "InvalidIpamScopeId.NotFound",
        "MissingParameter"
      ]
    },
    "deleteIpamPool": {
      "errors": [
        "IncorrectState",
        "InvalidIpamPoolId.NotFound",
        "MissingParameter"
      ]
    },
    "createIpamResourceDiscovery": {
      "errors": [
        "ResourceLimitExceeded"
      ]
    },
    "deleteIpamResourceDiscovery": {
      "errors": [
        "InvalidIpamResourceDiscoveryId.Malformed",
        "InvalidIpamResourceDiscoveryId.NotFound"
      ]
    },
    "createIpamScope": {
      "errors": [
        "InvalidIpamId.NotFound",
        "MissingParameter"
      ]
    },
    "deleteIpamScope": {
      "errors": [
        "DependencyViolation",
        "IncorrectState",
        "InvalidIpamScopeId.NotFound",
        "MissingParameter"
      ]
    },
    "createIpamPolicy": {
      "errors": [
        "InvalidIpamId.NotFound",
        "MissingParameter"
      ]
    },
    "deleteIpamPolicy": {
      "errors": [
        "InvalidIpamPolicyId.Malformed",
        "InvalidIpamPolicyId.NotFound",
        "MissingParameter"
      ]
    },
    "createRouteServer": {
      "errors": [
        "MissingParameter"
      ]
    },
    "deleteRouteServer": {
      "errors": [
        "IncorrectState",
        "InvalidRouteServerId.NotFound"
      ]
    },
    "createInstanceConnectEndpoint": {
      "errors": [
        "InvalidGroup.NotFound",
        "InvalidSubnetID.NotFound",
        "MissingParameter"
      ]
    },
    "deleteInstanceConnectEndpoint": {
      "errors": [
        "InvalidInstanceConnectEndpointId.Malformed",
        "InvalidInstanceConnectEndpointId.NotFound",
        "InvalidState",
        "MissingParameter"
      ]
    },
    "createVpcBlockPublicAccessExclusion": {
      "errors": [
        "InvalidVpcId.Malformed",
        "MissingParameter"
      ]
    },
    "deleteVpcBlockPublicAccessExclusion": {
      "errors": [
        "MissingParameter",
        "VpcBlockPublicAccessExclusionId.Malformed"
      ]
    },
    "createVpcEncryptionControl": {
      "errors": [
        "InvalidVpcId.Malformed",
        "MissingParameter"
      ]
    },
    "deleteVpcEncryptionControl": {
      "errors": [
        "InvalidVpcEncryptionControlId.Malformed",
        "InvalidVpcEncryptionControlId.NotFound",
        "MissingParameter"
      ]
    },
    "replaceNetworkAclAssociation": {
      "errors": [
        "DryRunOperation",
        "InvalidAssociationID.NotFound",
        "MissingParameter"
      ]
    },
    "acceptVpcEndpointConnections": {
      "errors": [
        "InvalidParameter",
        "InvalidVpcEndpointServiceId.NotFound"
      ]
    },
    "rejectVpcEndpointConnections": {
      "errors": [
        "InvalidParameter",
        "InvalidVpcEndpointServiceId.NotFound"
      ]
    },
    "modifyManagedPrefixList": {
      "errors": [
        "InvalidParameterCombination",
        "InvalidPrefixListID.NotFound",
        "InvalidPrefixListId.Malformed"
      ]
    },
    "modifySecurityGroupRules": {
      "errors": [
        "MissingParameter"
      ]
    },
    "allocateAddress": {
      "errors": [
        "AddressLimitExceeded"
      ]
    },
    "deleteKeyPair": {
      "errors": [
        "MissingParameter"
      ]
    },
    "createVolume": {
      "errors": [
        "InvalidZone.NotFound",
        "MissingParameter"
      ]
    },
    "createPlacementGroup": {
      "errors": [
        "InvalidParameterValue",
        "MissingParameter"
      ]
    },
    "describePlacementGroups": {
      "errors": [
        "InvalidParameterValue",
        "InvalidPlacementGroup.Unknown"
      ]
    },
    "releaseHosts": {
      "errors": [
        "MissingParameter"
      ]
    },
    "allocateHosts": {
      "errors": [
        "InvalidHostConfiguration",
        "InvalidRequest"
      ]
    },
    "describeHosts": {
      "errors": [
        "InvalidHostID.Malformed"
      ]
    },
    "cancelSpotFleetRequests": {
      "errors": [
        "InvalidParameterValue",
        "MissingParameter"
      ]
    },
    "cancelSpotInstanceRequests": {
      "errors": [
        "InvalidParameterCombination",
        "InvalidSpotInstanceRequestID.Malformed"
      ]
    },
    "requestSpotInstances": {
      "errors": [
        "MissingParameter"
      ]
    },
    "createSpotDatafeedSubscription": {
      "errors": [
        "InaccessibleStorageLocation"
      ]
    },
    "describeSpotDatafeedSubscription": {
      "errors": [
        "InvalidSpotDatafeed.NotFound"
      ]
    },
    "bundleInstance": {
      "errors": [
        "MissingParameter"
      ]
    },
    "cancelBundleTask": {
      "errors": [
        "InvalidBundleID.NotFound",
        "InvalidInstanceID.Malformed"
      ]
    },
    "describeBundleTasks": {
      "errors": [
        "InvalidBundleID.NotFound",
        "InvalidInstanceID.Malformed"
      ]
    },
    "getConsoleScreenshot": {
      "errors": [
        "InvalidInstanceID.Malformed",
        "InvalidInstanceID.NotFound"
      ]
    },
    "reportInstanceStatus": {
      "errors": [
        "MissingParameter"
      ]
    },
    "monitorInstances": {
      "errors": [
        "InvalidParameterValue",
        "MissingParameter"
      ]
    },
    "unmonitorInstances": {
      "errors": [
        "InvalidInstanceID.Malformed",
        "MissingParameter"
      ]
    },
    "confirmProductInstance": {
      "errors": [
        "AuthFailure"
      ]
    },
    "createNetworkInterfacePermission": {
      "errors": [
        "MissingParameter"
      ]
    },
    "modifyVolumeAttribute": {
      "errors": [
        "InvalidVolume.NotFound",
        "InvalidVolumeID.Malformed"
      ]
    },
    "describeVolumeAttribute": {
      "errors": [
        "InvalidParameterCombination",
        "InvalidParameterValue",
        "InvalidVolume.NotFound"
      ]
    },
    "resetSnapshotAttribute": {
      "errors": [
        "InvalidSnapshot.NotFound",
        "InvalidSnapshotID.Malformed",
        "MissingParameter"
      ]
    },
    "resetImageAttribute": {
      "errors": [
        "InvalidAMIID.Malformed",
        "InvalidAMIID.NotFound",
        "MissingParameter"
      ]
    },
    "describeImageAttribute": {
      "errors": [
        "InvalidAMIID.Malformed",
        "MissingParameter"
      ]
    },
    "describeRegions": {
      "errors": [
        "InvalidParameterValue"
      ]
    },
    "createTransitGatewayPeeringAttachment": {
      "errors": [
        "InvalidParameterValue",
        "InvalidTransitGatewayID.Malformed",
        "MissingParameter"
      ]
    },
    "rejectTransitGatewayPeeringAttachment": {
      "errors": [
        "InvalidTransitGatewayAttachmentID.NotFound",
        "MissingParameter"
      ]
    },
    "rejectTransitGatewayVpcAttachment": {
      "errors": [
        "InvalidTransitGatewayAttachmentID.NotFound",
        "MissingParameter"
      ]
    },
    "getTransitGatewayMulticastDomainAssociations": {
      "errors": [
        "InvalidTransitGatewayMulticastDomainId.Malformed",
        "InvalidTransitGatewayMulticastDomainId.NotFound",
        "MissingParameter"
      ]
    },
    "describeLaunchTemplateVersions": {
      "errors": [
        "InvalidLaunchTemplateId.Malformed",
        "MissingParameter"
      ]
    },
    "describeClientVpnConnections": {
      "errors": [
        "InvalidClientVpnEndpointId.NotFound",
        "MissingParameter"
      ]
    },
    "provisionIpamPoolCidr": {
      "errors": [
        "InvalidIpamPoolId.NotFound",
        "MissingParameter"
      ]
    },
    "deprovisionIpamPoolCidr": {
      "errors": [
        "InvalidIpamPoolId.NotFound",
        "MissingParameter"
      ]
    },
    "createCapacityReservation": {
      "errors": [
        "Unsupported"
      ]
    },
    "associateCapacityReservationBillingOwner": {
      "errors": [
        "InvalidCapacityReservationId.Malformed",
        "MissingParameter"
      ]
    },
    "cancelCapacityReservation": {
      "errors": [
        "InvalidCapacityReservationId.Malformed",
        "MissingParameter"
      ]
    },
    "disassociateCapacityReservationBillingOwner": {
      "errors": [
        "InvalidCapacityReservationId.Malformed",
        "MissingParameter"
      ]
    },
    "associateClientVpnTargetNetwork": {
      "errors": [
        "InvalidSubnetID.Malformed",
        "MissingParameter"
      ]
    },
    "disassociateClientVpnTargetNetwork": {
      "errors": [
        "InvalidClientVpnEndpointId.NotFound",
        "MissingParameter"
      ]
    },
    "provisionIpamByoasn": {
      "errors": [
        "MissingParameter"
      ]
    },
    "disassociateIpamByoasn": {
      "errors": [
        "InvalidCidr.NotFound"
      ]
    },
    "associateNatGatewayAddress": {
      "errors": [
        "MissingParameter",
        "NatGatewayMalformed",
        "NatGatewayNotFound"
      ]
    },
    "disassociateNatGatewayAddress": {
      "errors": [
        "MissingParameter",
        "NatGatewayMalformed",
        "NatGatewayNotFound"
      ]
    },
    "associateSecurityGroupVpc": {
      "errors": [
        "InvalidGroupId.Malformed",
        "MissingParameter"
      ]
    },
    "disassociateSecurityGroupVpc": {
      "errors": [
        "InvalidGroupId.Malformed",
        "MissingParameter"
      ]
    },
    "disassociateTransitGatewayMulticastDomain": {
      "errors": [
        "InvalidTransitGatewayMulticastDomainId.NotFound",
        "MissingParameter"
      ]
    },
    "createTransitGatewayPolicyTable": {
      "errors": [
        "IncorrectState",
        "InvalidTransitGatewayID.NotFound",
        "MissingParameter"
      ]
    },
    "disassociateTransitGatewayPolicyTable": {
      "errors": [
        "InvalidTransitGatewayPolicyTableId.Malformed",
        "InvalidTransitGatewayPolicyTableId.NotFound",
        "MissingParameter"
      ]
    },
    "disassociateTransitGatewayRouteTable": {
      "errors": [
        "InvalidRouteTableID.NotFound",
        "MissingParameter"
      ]
    },
    "attachClassicLinkVpc": {
      "errors": [
        "InvalidInstanceID.Malformed",
        "MissingParameter"
      ]
    },
    "detachClassicLinkVpc": {
      "errors": [
        "DependencyViolation",
        "InvalidInstanceID.Malformed",
        "InvalidVpcID.NotFound",
        "MissingParameter"
      ]
    },
    "createCoipCidr": {
      "errors": [
        "InvalidPoolID.Malformed",
        "InvalidPoolID.NotFound",
        "MissingParameter"
      ]
    },
    "deleteCoipCidr": {
      "errors": [
        "InvalidCidrBlock.Malformed",
        "InvalidIpv4PoolCoipId.Malformed",
        "MissingParameter"
      ]
    },
    "deleteLocalGatewayRouteTable": {
      "errors": [
        "InvalidLocalGatewayRouteTableID.NotFound",
        "MissingParameter"
      ]
    },
    "registerImage": {
      "errors": [
        "InvalidParameterCombination"
      ]
    },
    "createImageUsageReport": {
      "errors": [
        "MissingParameter"
      ]
    },
    "deleteImageUsageReport": {
      "errors": [
        "InvalidImageUsageReportId.Malformed",
        "MissingParameter"
      ]
    },
    "createIpamPrefixListResolver": {
      "errors": [
        "MissingParameter"
      ]
    },
    "deleteIpamPrefixListResolver": {
      "errors": [
        "InvalidIpamPrefixListResolverId.Malformed",
        "InvalidIpamPrefixListResolverId.NotFound",
        "MissingParameter"
      ]
    },
    "createIpamPrefixListResolverTarget": {
      "errors": [
        "InvalidIpamPrefixListResolverId.Malformed",
        "InvalidIpamPrefixListResolverId.NotFound",
        "MissingParameter"
      ]
    },
    "deleteIpamPrefixListResolverTarget": {
      "errors": [
        "InvalidIpamPrefixListResolverTargetId.Malformed",
        "MissingParameter"
      ]
    },
    "createLocalGatewayRoute": {
      "errors": [
        "InvalidParameterValue",
        "MissingParameter"
      ]
    },
    "deleteLocalGatewayRoute": {
      "errors": [
        "MissingParameter"
      ]
    },
    "deleteLocalGatewayRouteTableVirtualInterfaceGroupAssociation": {
      "errors": [
        "InvalidLocalGatewayRouteTableVirtualInterfaceGroupAssociationID.Malformed",
        "InvalidLocalGatewayRouteTableVirtualInterfaceGroupAssociationID.NotFound",
        "MissingParameter"
      ]
    },
    "createLocalGatewayVirtualInterfaceGroup": {
      "errors": [
        "InvalidLocalGatewayID.NotFound",
        "MissingParameter"
      ]
    },
    "createLocalGatewayRouteTableVirtualInterfaceGroupAssociation": {
      "errors": [
        "InvalidLocalGatewayRouteTableID.NotFound",
        "InvalidLocalGatewayVirtualInterfaceGroupID.Malformed",
        "MissingParameter"
      ]
    },
    "deleteLocalGatewayVirtualInterfaceGroup": {
      "errors": [
        "InvalidLocalGatewayVirtualInterfaceGroupID.Malformed",
        "InvalidLocalGatewayVirtualInterfaceGroupID.NotFound",
        "MissingParameter"
      ]
    },
    "createLocalGatewayRouteTableVpcAssociation": {
      "errors": [
        "InvalidLocalGatewayRouteTableID.Malformed",
        "InvalidLocalGatewayRouteTableID.NotFound",
        "InvalidVpcID.NotFound",
        "MissingParameter"
      ]
    },
    "deleteLocalGatewayRouteTableVpcAssociation": {
      "errors": [
        "InvalidLocalGatewayRouteTableVpcAssociationID.Malformed",
        "InvalidLocalGatewayRouteTableVpcAssociationID.NotFound",
        "MissingParameter"
      ]
    },
    "createLocalGatewayVirtualInterface": {
      "errors": [
        "InvalidLocalGatewayVirtualInterfaceGroupID.Malformed",
        "InvalidLocalGatewayVirtualInterfaceGroupID.NotFound",
        "MissingParameter"
      ]
    },
    "deleteLocalGatewayVirtualInterface": {
      "errors": [
        "InvalidLocalGatewayVirtualInterfaceID.Malformed",
        "InvalidLocalGatewayVirtualInterfaceID.NotFound",
        "MissingParameter"
      ]
    },
    "createRouteServerEndpoint": {
      "errors": [
        "InvalidRouteServerId.NotAssociated",
        "InvalidRouteServerId.NotFound",
        "InvalidSubnetID.Malformed",
        "MissingParameter"
      ]
    },
    "disassociateRouteServer": {
      "errors": [
        "InvalidRouteServerId.NotFound",
        "InvalidVpcID.NotFound",
        "MissingParameter"
      ]
    },
    "deleteRouteServerEndpoint": {
      "errors": [
        "InvalidRouteServerEndpointId.NotFound",
        "MissingParameter"
      ]
    },
    "createRouteServerPeer": {
      "errors": [
        "MissingParameter"
      ]
    },
    "deleteRouteServerPeer": {
      "errors": [
        "InvalidRouteServerPeerId.Malformed",
        "InvalidRouteServerPeerId.NotFound",
        "MissingParameter"
      ]
    },
    "createTrafficMirrorFilterRule": {
      "errors": [
        "MissingParameter"
      ]
    },
    "deleteTrafficMirrorFilterRule": {
      "errors": [
        "InvalidParameterValue",
        "InvalidTrafficMirrorFilterRuleId.NotFound",
        "MissingParameter"
      ]
    },
    "createTrafficMirrorSession": {
      "errors": [
        "InvalidNetworkInterfaceID.NotFound",
        "InvalidParameterValue",
        "MissingParameter"
      ]
    },
    "createTrafficMirrorTarget": {
      "errors": [
        "InvalidParameterCombination"
      ]
    },
    "createTransitGatewayMeteringPolicy": {
      "errors": [
        "IncorrectState",
        "InvalidTransitGatewayID.NotFound",
        "MissingParameter"
      ]
    },
    "deleteTransitGatewayMeteringPolicy": {
      "errors": [
        "InvalidTransitGatewayMeteringPolicyId.NotFound",
        "InvalidTransitGatewayMeteringPolicyIdMalformedException",
        "MissingParameter"
      ]
    },
    "createTransitGatewayMeteringPolicyEntry": {
      "errors": [
        "MissingParameter"
      ]
    },
    "deleteTransitGatewayMeteringPolicyEntry": {
      "errors": [
        "InvalidTransitGatewayMeteringPolicyId.NotFound",
        "InvalidTransitGatewayMeteringPolicyIdMalformedException",
        "MissingParameter"
      ]
    },
    "createTransitGatewayPrefixListReference": {
      "errors": [
        "MissingParameter"
      ]
    },
    "deleteTransitGatewayPrefixListReference": {
      "errors": [
        "InvalidRouteTableID.NotFound",
        "MissingParameter"
      ]
    },
    "createTransitGatewayRoute": {
      "errors": [
        "InvalidRouteTableID.NotFound",
        "MissingParameter"
      ]
    },
    "deleteTransitGatewayRoute": {
      "errors": [
        "InvalidParameterValue",
        "MissingParameter"
      ]
    },
    "createTransitGatewayRouteTableAnnouncement": {
      "errors": [
        "InvalidRouteTableID.NotFound",
        "InvalidTransitGatewayAttachmentID.Malformed",
        "MissingParameter"
      ]
    },
    "deleteTransitGatewayRouteTableAnnouncement": {
      "errors": [
        "InvalidTransitGatewayRouteTableAnnouncementId.Malformed",
        "MissingParameter"
      ]
    },
    "createVerifiedAccessEndpoint": {
      "errors": [
        "MissingParameter"
      ]
    },
    "createVpnConnectionRoute": {
      "errors": [
        "InvalidParameter",
        "MissingParameter"
      ]
    },
    "deleteVpnConnectionRoute": {
      "errors": [
        "InvalidRoute.Malformed",
        "MissingParameter"
      ]
    },
    "startNetworkInsightsAccessScopeAnalysis": {
      "errors": [
        "IdempotentParameterMismatch",
        "InvalidParameterValue"
      ]
    },
    "deleteNetworkInsightsAccessScopeAnalysis": {
      "errors": [
        "InvalidParameterValue",
        "MissingParameter"
      ]
    },
    "startNetworkInsightsAnalysis": {
      "errors": [
        "InvalidParameterValue",
        "MissingParameter"
      ]
    },
    "deleteNetworkInsightsAnalysis": {
      "errors": [
        "InvalidParameterValue",
        "MissingParameter"
      ]
    },
    "provisionPublicIpv4PoolCidr": {
      "errors": [
        "InvalidIpamPoolId.NotFound",
        "MissingParameter"
      ]
    },
    "deprovisionPublicIpv4PoolCidr": {
      "errors": [
        "InvalidPublicIpv4Pool.NotFound",
        "InvalidPublicIpv4PoolID.Malformed",
        "MissingParameter"
      ]
    },
    "deregisterTransitGatewayMulticastGroupMembers": {
      "errors": [
        "MissingParameter"
      ]
    },
    "registerTransitGatewayMulticastGroupMembers": {
      "errors": [
        "InvalidNetworkInterfaceId.Malformed",
        "MissingParameter"
      ]
    },
    "deregisterTransitGatewayMulticastGroupSources": {
      "errors": [
        "MissingParameter"
      ]
    },
    "registerTransitGatewayMulticastGroupSources": {
      "errors": [
        "InvalidNetworkInterfaceId.Malformed",
        "MissingParameter"
      ]
    },
    "describeByoipCidrs": {
      "errors": [
        "MissingParameter"
      ]
    },
    "getIpamPoolCidrs": {
      "errors": [
        "InvalidIpamPoolId.NotFound",
        "MissingParameter"
      ]
    },
    "describeClientVpnTargetNetworks": {
      "errors": [
        "InvalidClientVpnEndpointId.NotFound",
        "MissingParameter"
      ]
    },
    "getTransitGatewayPrefixListReferences": {
      "errors": [
        "InvalidRouteTableID.NotFound",
        "MissingParameter"
      ]
    },
    "searchTransitGatewayRoutes": {
      "errors": [
        "InvalidRouteTableID.NotFound",
        "MissingParameter"
      ]
    },
    "searchLocalGatewayRoutes": {
      "errors": [
        "InvalidLocalGatewayRouteTableID.NotFound",
        "MissingParameter"
      ]
    },
    "describeClientVpnRoutes": {
      "errors": [
        "InvalidClientVpnEndpointId.NotFound",
        "MissingParameter"
      ]
    },
    "getSubnetCidrReservations": {
      "errors": [
        "InvalidSubnetID.NotFound",
        "MissingParameter"
      ]
    },
    "describeVpcBlockPublicAccessExclusions": {
      "errors": [
        "MissingParameter",
        "VpcBlockPublicAccessExclusionId.Malformed"
      ]
    },
    "getIpamPoolAllocations": {
      "errors": [
        "InvalidIpamPoolId.NotFound",
        "MissingParameter"
      ]
    },
    "deleteTransitGatewayPeeringAttachment": {
      "errors": [
        "InvalidTransitGatewayAttachmentID.NotFound"
      ]
    },
    "deprovisionIpamByoasn": {
      "errors": [
        "InvalidIpamId.NotFound",
        "MissingParameter"
      ]
    },
    "deleteTransitGatewayPolicyTable": {
      "errors": [
        "InvalidTransitGatewayPolicyTableId.Malformed",
        "InvalidTransitGatewayPolicyTableId.NotFound",
        "MissingParameter"
      ]
    },
    "createIpamExternalResourceVerificationToken": {
      "errors": [
        "InvalidIpamId.NotFound",
        "MissingParameter"
      ]
    },
    "deleteIpamExternalResourceVerificationToken": {
      "errors": [
        "InvalidIpamExternalResourceVerificationTokenId.Malformed",
        "InvalidIpamExternalResourceVerificationTokenId.NotFound",
        "MissingParameter"
      ]
    },
    "cancelConversion": {
      "errors": [
        "InvalidAction"
      ]
    },
    "cancelDeclarativePoliciesReport": {
      "errors": [
        "InvalidDeclarativePoliciesReportId.Malformed"
      ]
    },
    "cancelExportTask": {
      "errors": [
        "InvalidID"
      ]
    },
    "cancelImageLaunchPermission": {
      "errors": [
        "InvalidAMIID.Malformed"
      ]
    },
    "cancelImportTask": {
      "errors": [
        "InvalidConversionTaskId.Malformed"
      ]
    },
    "cancelReservedInstancesListing": {
      "errors": [
        "InvalidInput"
      ]
    },
    "deleteCapacityManagerDataExport": {
      "errors": [
        "InvalidCapacityManagerDataExportId.Malformed",
        "InvalidCapacityManagerDataExportId.NotFound"
      ]
    },
    "deleteClientVpnRoute": {
      "errors": [
        "InvalidClientVpnEndpointId.NotFound"
      ]
    },
    "deleteFpgaImage": {
      "errors": [
        "InvalidFpgaImageID.Malformed"
      ]
    },
    "deleteInstanceEventWindow": {
      "errors": [
        "InvalidInstanceEventWindowIDNotFound",
        "InvalidParameterValue"
      ]
    },
    "deleteLaunchTemplateVersions": {
      "errors": [
        "MissingParameter"
      ]
    },
    "deletePublicIpv4Pool": {
      "errors": [
        "InvalidPublicIpv4Pool.NotFound",
        "InvalidPublicIpv4PoolID.Malformed"
      ]
    },
    "deleteTransitGatewayConnect": {
      "errors": [
        "InvalidTransitGatewayAttachmentID.NotFound"
      ]
    },
    "deleteTransitGatewayConnectPeer": {
      "errors": [
        "InvalidTransitGatewayConnectPeerID.Malformed",
        "InvalidTransitGatewayConnectPeerID.NotFound"
      ]
    },
    "deleteTransitGatewayMulticastDomain": {
      "errors": [
        "InvalidTransitGatewayMulticastDomainId.Malformed",
        "InvalidTransitGatewayMulticastDomainId.NotFound"
      ]
    },
    "deleteVpnConcentrator": {
      "errors": [
        "InvalidVpnConcentratorID.Malformed"
      ]
    },
    "deprovisionByoipCidr": {
      "errors": [
        "RequestLimitExceeded"
      ]
    },
    "deregisterInstanceEventNotificationAttributes": {
      "errors": [
        "MissingParameter"
      ]
    },
    "rejectCapacityReservationBillingOwnership": {
      "errors": [
        "InvalidCapacityReservationId.Malformed"
      ]
    },
    "rejectTransitGatewayMulticastDomainAssociations": {
      "errors": [
        "MissingParameter"
      ]
    },
    "releaseIpamPoolAllocation": {
      "errors": [
        "InvalidIpamPoolId.NotFound"
      ]
    },
    "terminateClientVpnConnections": {
      "errors": [
        "MissingParameter"
      ]
    },
    "withdrawByoipCidr": {
      "errors": [
        "RequestLimitExceeded"
      ]
    },
    "allocateIpamPoolCidr": {
      "errors": [
        "InvalidIpamPoolId.NotFound"
      ]
    },
    "associateEnclaveCertificateIamRole": {
      "errors": [
        "InvalidCertificateArn.Malformed",
        "InvalidRoleArn.Malformed"
      ]
    },
    "associateIamInstanceProfile": {
      "errors": [
        "MissingParameter"
      ]
    },
    "associateIpamResourceDiscovery": {
      "errors": [
        "InvalidIpamResourceDiscoveryId.Malformed",
        "InvalidIpamResourceDiscoveryId.NotFound"
      ]
    },
    "associateRouteServer": {
      "errors": [
        "InvalidRouteServerId.NotFound"
      ]
    },
    "associateTransitGatewayPolicyTable": {
      "errors": [
        "InvalidTransitGatewayPolicyTableId.Malformed",
        "InvalidTransitGatewayPolicyTableId.NotFound"
      ]
    },
    "associateTransitGatewayRouteTable": {
      "errors": [
        "InvalidRouteTableID.NotFound"
      ]
    },
    "associateTrunkInterface": {
      "errors": [
        "OperationNotPermitted"
      ]
    },
    "attachVerifiedAccessTrustProvider": {
      "errors": [
        "InvalidVerifiedAccessInstanceId.NotFound"
      ]
    },
    "copyFpgaImage": {
      "errors": [
        "InvalidFpgaImageID.Malformed"
      ]
    },
    "copyVolumes": {
      "errors": [
        "InvalidVolumeID.Malformed"
      ]
    },
    "createCapacityManagerDataExport": {
      "errors": [
        "MissingParameter"
      ]
    },
    "createCapacityReservationBySplitting": {
      "errors": [
        "InvalidCapacityReservationId.Malformed",
        "InvalidCapacityReservationId.NotFound"
      ]
    },
    "createClientVpnRoute": {
      "errors": [
        "InvalidClientVpnEndpointId.NotFound"
      ]
    },
    "createDelegateMacVolumeOwnershipTask": {
      "errors": [
        "MissingParameter"
      ]
    },
    "createInstanceExportTask": {
      "errors": [
        "MissingParameter"
      ]
    },
    "createInterruptibleCapacityReservationAllocation": {
      "errors": [
        "InvalidCapacityReservationId.NotFound"
      ]
    },
    "createReplaceRootVolumeTask": {
      "errors": [
        "InvalidInstanceID.Malformed"
      ]
    },
    "createReservedInstancesListing": {
      "errors": [
        "MissingParameter"
      ]
    },
    "createStoreImageTask": {
      "errors": [
        "InvalidAMIID.Malformed"
      ]
    },
    "createTransitGatewayConnect": {
      "errors": [
        "MissingParameter"
      ]
    },
    "createTransitGatewayConnectPeer": {
      "errors": [
        "MissingParameter"
      ]
    },
    "createVpcEndpointConnectionNotification": {
      "errors": [
        "InvalidParameter"
      ]
    },
    "importKeyPair": {
      "errors": [
        "InvalidKeyPair.Duplicate"
      ]
    },
    "purchaseCapacityBlock": {
      "errors": [
        "MissingParameter"
      ]
    },
    "purchaseCapacityBlockExtension": {
      "errors": [
        "InvalidCapacityReservationId.NotFound"
      ]
    },
    "runScheduledInstances": {
      "errors": [
        "InvalidScheduledInstance"
      ]
    },
    "startDeclarativePoliciesReport": {
      "errors": [
        "DeclarativePoliciesAccessDenied"
      ]
    },
    "startVpcEndpointServicePrivateDnsVerification": {
      "errors": [
        "InvalidVpcEndpointServiceId.Malformed",
        "InvalidVpcEndpointServiceId.NotFound"
      ]
    },
    "acceptAddressTransfer": {
      "errors": [
        "InvalidAddress.Malformed",
        "InvalidAddress.NotFound"
      ]
    },
    "acceptCapacityReservationBillingOwnership": {
      "errors": [
        "InvalidCapacityReservationId.Malformed"
      ]
    },
    "acceptTransitGatewayPeeringAttachment": {
      "errors": [
        "InvalidTransitGatewayAttachmentID.NotFound"
      ]
    },
    "acceptTransitGatewayVpcAttachment": {
      "errors": [
        "InvalidTransitGatewayAttachmentID.NotFound"
      ]
    },
    "assignPrivateNatGatewayAddress": {
      "errors": [
        "NatGatewayNotFound"
      ]
    },
    "describeCapacityBlockExtensionOfferings": {
      "errors": [
        "InvalidCapacityReservationId.NotFound"
      ]
    },
    "describeFleetHistory": {
      "errors": [
        "InvalidFleetId.Malformed"
      ]
    },
    "describeFleetInstances": {
      "errors": [
        "InvalidFleetId.Malformed"
      ]
    },
    "describeFpgaImageAttribute": {
      "errors": [
        "InvalidFpgaImageID.Malformed",
        "InvalidFpgaImageID.NotFound"
      ]
    },
    "describeIdentityIdFormat": {
      "errors": [
        "InvalidTargetArn.Unknown"
      ]
    },
    "describeStaleSecurityGroups": {
      "errors": [
        "InvalidVpcID.NotFound"
      ]
    },
    "describeVpcEndpointServicePermissions": {
      "errors": [
        "InvalidVpcEndpointServiceId.Malformed",
        "InvalidVpcEndpointServiceId.NotFound"
      ]
    },
    "detachVerifiedAccessTrustProvider": {
      "errors": [
        "DependencyViolation",
        "InvalidVerifiedAccessInstanceId.NotFound"
      ]
    },
    "disableAddressTransfer": {
      "errors": [
        "InvalidElasticIpID.NotFound"
      ]
    },
    "disableFastLaunch": {
      "errors": [
        "InvalidRequest"
      ]
    },
    "disableImage": {
      "errors": [
        "InvalidAMIID.Malformed"
      ]
    },
    "disableImageDeprecation": {
      "errors": [
        "InvalidAMIID.Malformed"
      ]
    },
    "disableImageDeregistrationProtection": {
      "errors": [
        "InvalidAMIID.Malformed"
      ]
    },
    "disableIpamPolicy": {
      "errors": [
        "InvalidIpamPolicyId.Malformed",
        "InvalidIpamPolicyId.NotFound"
      ]
    },
    "disableRouteServerPropagation": {
      "errors": [
        "InvalidRouteServerId.NotFound"
      ]
    },
    "disableTransitGatewayRouteTablePropagation": {
      "errors": [
        "MissingParameter"
      ]
    },
    "disableVgwRoutePropagation": {
      "errors": [
        "InvalidRouteTableID.NotFound"
      ]
    },
    "disassociateEnclaveCertificateIamRole": {
      "errors": [
        "InvalidCertificateArn.Malformed",
        "InvalidRoleArn.Malformed"
      ]
    },
    "disassociateIamInstanceProfile": {
      "errors": [
        "InvalidParameterValue"
      ]
    },
    "disassociateInstanceEventWindow": {
      "errors": [
        "DependencyViolation",
        "MissingParameter"
      ]
    },
    "disassociateIpamResourceDiscovery": {
      "errors": [
        "InvalidIpamResourceDiscoveryAssociationId.Malformed",
        "InvalidIpamResourceDiscoveryAssociationId.NotFound"
      ]
    },
    "disassociateTrunkInterface": {
      "errors": [
        "OperationNotPermitted"
      ]
    },
    "enableAddressTransfer": {
      "errors": [
        "InvalidParameterValue"
      ]
    },
    "enableFastLaunch": {
      "errors": [
        "InvalidRequest"
      ]
    },
    "enableImage": {
      "errors": [
        "InvalidAMIID.Malformed"
      ]
    },
    "enableImageBlockPublicAccess": {
      "errors": [
        "InvalidParameterValue"
      ]
    },
    "enableImageDeprecation": {
      "errors": [
        "MissingParameter"
      ]
    },
    "enableImageDeregistrationProtection": {
      "errors": [
        "InvalidAMIID.Malformed"
      ]
    },
    "enableIpamPolicy": {
      "errors": [
        "InvalidIpamPolicyId.Malformed",
        "InvalidIpamPolicyId.NotFound"
      ]
    },
    "enableRouteServerPropagation": {
      "errors": [
        "InvalidRouteServerId.NotFound"
      ]
    },
    "enableTransitGatewayRouteTablePropagation": {
      "errors": [
        "MissingParameter"
      ]
    },
    "enableVgwRoutePropagation": {
      "errors": [
        "InvalidRouteTableID.NotFound"
      ]
    },
    "exportImage": {
      "errors": [
        "MissingParameter"
      ]
    },
    "exportTransitGatewayRoutes": {
      "errors": [
        "InvalidRouteTableID.NotFound"
      ]
    },
    "exportVerifiedAccessInstanceClientConfiguration": {
      "errors": [
        "InvalidVerifiedAccessInstanceId.NotFound"
      ]
    },
    "getActiveVpnTunnelStatus": {
      "errors": [
        "InvalidVpnConnectionID.NotFound"
      ]
    },
    "getAssociatedEnclaveCertificateIamRoles": {
      "errors": [
        "InvalidCertificateArn.Malformed",
        "UnauthorizedOperation"
      ]
    },
    "getAssociatedIpv6PoolCidrs": {
      "errors": [
        "InvalidIpv6PoolID.Malformed"
      ]
    },
    "getCapacityReservationUsage": {
      "errors": [
        "InvalidCapacityReservationId.Malformed"
      ]
    },
    "getCoipPoolUsage": {
      "errors": [
        "InvalidPoolID.Malformed"
      ]
    },
    "getDeclarativePoliciesReportSummary": {
      "errors": [
        "InvalidDeclarativePoliciesReportId.Malformed"
      ]
    },
    "getGroupsForCapacityReservation": {
      "errors": [
        "InvalidCapacityReservationId.Malformed"
      ]
    },
    "getImageAncestry": {
      "errors": [
        "InvalidAMIID.Malformed"
      ]
    },
    "getInstanceTpmEkPub": {
      "errors": [
        "MissingParameter"
      ]
    },
    "getInstanceUefiData": {
      "errors": [
        "InvalidInstanceID.Malformed"
      ]
    },
    "getIpamAddressHistory": {
      "errors": [
        "InvalidIpamScopeId.NotFound"
      ]
    },
    "getIpamDiscoveredAccounts": {
      "errors": [
        "InvalidIpamResourceDiscoveryId.Malformed",
        "InvalidIpamResourceDiscoveryId.NotFound"
      ]
    },
    "getIpamDiscoveredPublicAddresses": {
      "errors": [
        "InvalidIpamResourceDiscoveryId.Malformed",
        "InvalidIpamResourceDiscoveryId.NotFound"
      ]
    },
    "getIpamDiscoveredResourceCidrs": {
      "errors": [
        "InvalidIpamResourceDiscoveryId.Malformed",
        "InvalidIpamResourceDiscoveryId.NotFound"
      ]
    },
    "getIpamPolicyAllocationRules": {
      "errors": [
        "InvalidIpamPolicyId.Malformed",
        "InvalidIpamPolicyId.NotFound"
      ]
    },
    "getIpamPolicyOrganizationTargets": {
      "errors": [
        "InvalidIpamPolicyId.Malformed",
        "InvalidIpamPolicyId.NotFound"
      ]
    },
    "getIpamPrefixListResolverRules": {
      "errors": [
        "InvalidIpamPrefixListResolverId.Malformed",
        "InvalidIpamPrefixListResolverId.NotFound"
      ]
    },
    "getIpamPrefixListResolverVersionEntries": {
      "errors": [
        "MissingParameter"
      ]
    },
    "getIpamPrefixListResolverVersions": {
      "errors": [
        "InvalidIpamPrefixListResolverId.Malformed",
        "InvalidIpamPrefixListResolverId.NotFound"
      ]
    },
    "getIpamResourceCidrs": {
      "errors": [
        "InvalidIpamPoolId.NotFound",
        "InvalidIpamScopeId.NotFound"
      ]
    },
    "getLaunchTemplateData": {
      "errors": [
        "InvalidInstanceID.Malformed"
      ]
    },
    "getManagedPrefixListAssociations": {
      "errors": [
        "InvalidPrefixListID.NotFound",
        "InvalidPrefixListId.Malformed"
      ]
    },
    "getNetworkInsightsAccessScopeAnalysisFindings": {
      "errors": [
        "InvalidParameterValue"
      ]
    },
    "getNetworkInsightsAccessScopeContent": {
      "errors": [
        "InvalidParameterValue"
      ]
    },
    "getRouteServerAssociations": {
      "errors": [
        "InvalidRouteServerId.NotFound"
      ]
    },
    "getRouteServerPropagations": {
      "errors": [
        "InvalidRouteServerId.NotFound"
      ]
    },
    "getRouteServerRoutingDatabase": {
      "errors": [
        "InvalidRouteServerId.NotFound"
      ]
    },
    "getTransitGatewayAttachmentPropagations": {
      "errors": [
        "InvalidTransitGatewayAttachmentID.NotFound"
      ]
    },
    "getTransitGatewayMeteringPolicyEntries": {
      "errors": [
        "InvalidTransitGatewayMeteringPolicyId.NotFound",
        "InvalidTransitGatewayMeteringPolicyIdMalformedException"
      ]
    },
    "getTransitGatewayPolicyTableAssociations": {
      "errors": [
        "InvalidTransitGatewayPolicyTableId.Malformed",
        "InvalidTransitGatewayPolicyTableId.NotFound"
      ]
    },
    "getTransitGatewayPolicyTableEntries": {
      "errors": [
        "InvalidTransitGatewayPolicyTableId.Malformed",
        "InvalidTransitGatewayPolicyTableId.NotFound"
      ]
    },
    "getTransitGatewayRouteTableAssociations": {
      "errors": [
        "InvalidRouteTableID.NotFound"
      ]
    },
    "getTransitGatewayRouteTablePropagations": {
      "errors": [
        "InvalidRouteTableID.NotFound"
      ]
    },
    "getVerifiedAccessEndpointPolicy": {
      "errors": [
        "InvalidParameterValue",
        "InvalidVerifiedAccessEndpointId.NotFound"
      ]
    },
    "getVerifiedAccessEndpointTargets": {
      "errors": [
        "InvalidVerifiedAccessEndpointId.NotFound"
      ]
    },
    "getVerifiedAccessGroupPolicy": {
      "errors": [
        "InvalidVerifiedAccessGroupId.NotFound"
      ]
    },
    "getVpcResourcesBlockingEncryptionEnforcement": {
      "errors": [
        "InvalidVpcId.Malformed"
      ]
    },
    "getVpnConnectionDeviceSampleConfiguration": {
      "errors": [
        "InvalidVpnConnectionDeviceTypeId.NotFound"
      ]
    },
    "getVpnTunnelReplacementStatus": {
      "errors": [
        "InvalidVpnConnectionId"
      ]
    },
    "lockSnapshot": {
      "errors": [
        "MissingParameter"
      ]
    },
    "modifyAddressAttribute": {
      "errors": [
        "InvalidAllocationID.NotFound",
        "InvalidElasticIpID.NotFound"
      ]
    },
    "modifyAvailabilityZoneGroup": {
      "errors": [
        "MissingParameter"
      ]
    },
    "modifyCapacityReservation": {
      "errors": [
        "InvalidCapacityReservationId.Malformed"
      ]
    },
    "modifyCapacityReservationFleet": {
      "errors": [
        "InvalidCapacityReservationFleetId.Malformed"
      ]
    },
    "modifyFleet": {
      "errors": [
        "InvalidFleetId.Malformed"
      ]
    },
    "modifyFpgaImageAttribute": {
      "errors": [
        "InvalidFpgaImageID.Malformed",
        "InvalidFpgaImageID.NotFound"
      ]
    },
    "modifyInstanceCapacityReservationAttributes": {
      "errors": [
        "InvalidParameterValue"
      ]
    },
    "modifyInstanceConnectEndpoint": {
      "errors": [
        "InvalidInstanceConnectEndpointId.Malformed",
        "InvalidInstanceConnectEndpointId.NotFound"
      ]
    },
    "modifyInstanceCpuOptions": {
      "errors": [
        "InvalidInstanceID.Malformed"
      ]
    },
    "modifyInstanceEventStartTime": {
      "errors": [
        "MissingParameter"
      ]
    },
    "modifyInstanceEventWindow": {
      "errors": [
        "InvalidInstanceEventWindowIDNotFound",
        "InvalidInstanceEventWindowId.Malformed"
      ]
    },
    "modifyInstanceMaintenanceOptions": {
      "errors": [
        "InvalidInstanceID.Malformed"
      ]
    },
    "modifyInstanceMetadataOptions": {
      "errors": [
        "InvalidInstanceID.Malformed"
      ]
    },
    "modifyInstanceNetworkPerformance": {
      "errors": [
        "InvalidAction"
      ]
    },
    "modifyInstancePlacement": {
      "errors": [
        "InvalidInstanceID.Malformed"
      ]
    },
    "modifyIpam": {
      "errors": [
        "InvalidParameterCombination"
      ]
    },
    "modifyIpamPolicyAllocationRules": {
      "errors": [
        "MissingParameter"
      ]
    },
    "modifyIpamPool": {
      "errors": [
        "InvalidIpamPoolId.NotFound"
      ]
    },
    "modifyIpamPrefixListResolver": {
      "errors": [
        "InvalidIpamPrefixListResolverId.Malformed",
        "InvalidIpamPrefixListResolverId.NotFound"
      ]
    },
    "modifyIpamPrefixListResolverTarget": {
      "errors": [
        "InvalidIpamPrefixListResolverTargetId.Malformed"
      ]
    },
    "modifyIpamResourceCidr": {
      "errors": [
        "InvalidIpamScopeId.Malformed",
        "InvalidParameterValue"
      ]
    },
    "modifyIpamResourceDiscovery": {
      "errors": [
        "InvalidIpamResourceDiscoveryId.Malformed",
        "InvalidIpamResourceDiscoveryId.NotFound"
      ]
    },
    "modifyIpamScope": {
      "errors": [
        "InvalidParameterCombination"
      ]
    },
    "modifyLocalGatewayRoute": {
      "errors": [
        "MissingParameter"
      ]
    },
    "modifyPrivateDnsNameOptions": {
      "errors": [
        "UnknownResource"
      ]
    },
    "modifyPublicIpDnsNameOptions": {
      "errors": [
        "MissingParameter"
      ]
    },
    "modifyRouteServer": {
      "errors": [
        "InvalidRouteServerId.NotFound"
      ]
    },
    "modifySnapshotTier": {
      "errors": [
        "InvalidParameterValue"
      ]
    },
    "modifyTrafficMirrorFilterNetworkServices": {
      "errors": [
        "InvalidParameterValue"
      ]
    },
    "modifyTrafficMirrorFilterRule": {
      "errors": [
        "InvalidParameterValue",
        "InvalidTrafficMirrorFilterRuleId.NotFound"
      ]
    },
    "modifyTrafficMirrorSession": {
      "errors": [
        "InvalidParameterValue"
      ]
    },
    "modifyTransitGateway": {
      "errors": [
        "MissingParameter"
      ]
    },
    "modifyTransitGatewayMeteringPolicy": {
      "errors": [
        "InvalidTransitGatewayMeteringPolicyIdMalformedException",
        "MissingParameter"
      ]
    },
    "modifyTransitGatewayPrefixListReference": {
      "errors": [
        "MissingParameter"
      ]
    },
    "modifyTransitGatewayVpcAttachment": {
      "errors": [
        "InvalidTransitGatewayAttachmentID.NotFound"
      ]
    },
    "modifyVerifiedAccessEndpoint": {
      "errors": [
        "InvalidParameterValue",
        "InvalidVerifiedAccessEndpointId.NotFound"
      ]
    },
    "modifyVerifiedAccessEndpointPolicy": {
      "errors": [
        "InvalidParameterValue",
        "InvalidVerifiedAccessEndpointId.NotFound"
      ]
    },
    "modifyVerifiedAccessGroup": {
      "errors": [
        "InvalidVerifiedAccessGroupId.NotFound"
      ]
    },
    "modifyVerifiedAccessGroupPolicy": {
      "errors": [
        "InvalidVerifiedAccessGroupId.NotFound"
      ]
    },
    "modifyVerifiedAccessInstance": {
      "errors": [
        "InvalidVerifiedAccessInstanceId.NotFound"
      ]
    },
    "modifyVerifiedAccessInstanceLoggingConfiguration": {
      "errors": [
        "MissingParameter"
      ]
    },
    "modifyVerifiedAccessTrustProvider": {
      "errors": [
        "InvalidVerifiedAccessTrustProviderId.NotFound"
      ]
    },
    "modifyVpcEncryptionControl": {
      "errors": [
        "InvalidVpcEncryptionControlId.Malformed",
        "InvalidVpcEncryptionControlId.NotFound"
      ]
    },
    "modifyVpcEndpointConnectionNotification": {
      "errors": [
        "InvalidConnectionNotification",
        "InvalidParameter"
      ]
    },
    "modifyVpcEndpointServicePayerResponsibility": {
      "errors": [
        "UnsupportedOperation"
      ]
    },
    "modifyVpcEndpointServicePermissions": {
      "errors": [
        "InvalidVpcEndpointServiceId.Malformed",
        "InvalidVpcEndpointServiceId.NotFound"
      ]
    },
    "modifyVpnConnection": {
      "errors": [
        "InvalidVpnConnectionId"
      ]
    },
    "modifyVpnConnectionOptions": {
      "errors": [
        "InvalidVpnConnectionID.NotFound"
      ]
    },
    "modifyVpnTunnelCertificate": {
      "errors": [
        "InvalidParameterValue"
      ]
    },
    "modifyVpnTunnelOptions": {
      "errors": [
        "InvalidVpnConnectionId"
      ]
    },
    "moveByoipCidrToIpam": {
      "errors": [
        "InvalidIpamPoolId.NotFound"
      ]
    },
    "moveCapacityReservationInstances": {
      "errors": [
        "InvalidCapacityReservationId.Malformed"
      ]
    },
    "replaceTransitGatewayRoute": {
      "errors": [
        "InvalidRouteTableID.NotFound"
      ]
    },
    "replaceVpnTunnel": {
      "errors": [
        "InvalidVpnConnectionId"
      ]
    },
    "resetAddressAttribute": {
      "errors": [
        "MissingParameter"
      ]
    },
    "resetFpgaImageAttribute": {
      "errors": [
        "InvalidFpgaImageID.Malformed"
      ]
    },
    "resetInstanceAttribute": {
      "errors": [
        "InvalidParameterValue"
      ]
    },
    "resetNetworkInterfaceAttribute": {
      "errors": [
        "InvalidParameterCombination"
      ]
    },
    "restoreImageFromRecycleBin": {
      "errors": [
        "InvalidAMIID.Malformed"
      ]
    },
    "restoreManagedPrefixListVersion": {
      "errors": [
        "MissingParameter"
      ]
    },
    "restoreSnapshotFromRecycleBin": {
      "errors": [
        "InvalidSnapshotID.Malformed"
      ]
    },
    "restoreSnapshotTier": {
      "errors": [
        "InvalidSnapshotID.Malformed"
      ]
    },
    "restoreVolumeFromRecycleBin": {
      "errors": [
        "InvalidVolumeID.Malformed"
      ]
    },
    "searchTransitGatewayMulticastGroups": {
      "errors": [
        "InvalidTransitGatewayMulticastDomainId.Malformed",
        "InvalidTransitGatewayMulticastDomainId.NotFound"
      ]
    },
    "sendDiagnosticInterrupt": {
      "errors": [
        "InvalidInstanceID.Malformed"
      ]
    },
    "unlockSnapshot": {
      "errors": [
        "InvalidSnapshotID.Malformed"
      ]
    },
    "updateInterruptibleCapacityReservationAllocation": {
      "errors": [
        "InvalidCapacityReservationId.NotFound"
      ]
    },
    "acceptReservedInstancesExchangeQuote": {
      "errors": [
        "InvalidReservedInstancesID.NotFound"
      ]
    },
    "applySecurityGroupsToClientVpnTargetNetwork": {
      "errors": [
        "InvalidVpcId.Malformed"
      ]
    },
    "associateTransitGatewayMulticastDomain": {
      "errors": [
        "InvalidTransitGatewayMulticastDomainId.NotFound"
      ]
    },
    "cancelCapacityReservationFleets": {
      "errors": [
        "InvalidCapacityReservationFleetId.Malformed"
      ]
    },
    "deleteFleets": {
      "errors": [
        "InvalidFleetId.Malformed"
      ]
    },
    "deleteQueuedReservedInstances": {
      "errors": [
        "InvalidReservedInstancesID.NotFound"
      ]
    },
    "describeCapacityBlockExtensionHistory": {
      "errors": [
        "InvalidCapacityReservationId.Malformed"
      ]
    },
    "describeCapacityBlockStatus": {
      "errors": [
        "InvalidCapacityBlockId.Malformed"
      ]
    },
    "describeCapacityBlocks": {
      "errors": [
        "InvalidCapacityBlockId.Malformed"
      ]
    },
    "describeCapacityManagerDataExports": {
      "errors": [
        "InvalidCapacityManagerDataExportId.NotFound"
      ]
    },
    "describeCapacityReservationBillingRequests": {
      "errors": [
        "MissingParameter"
      ]
    },
    "describeCapacityReservationFleets": {
      "errors": [
        "InvalidCapacityReservationFleetId.Malformed"
      ]
    },
    "describeCapacityReservations": {
      "errors": [
        "InvalidCapacityReservationId.Malformed"
      ]
    },
    "describeClassicLinkInstances": {
      "errors": [
        "InvalidInstanceID.Malformed"
      ]
    },
    "describeClientVpnEndpoints": {
      "errors": [
        "InvalidClientVpnEndpointId.NotFound"
      ]
    },
    "describeCoipPools": {
      "errors": [
        "InvalidPoolID.Malformed"
      ]
    },
    "describeDeclarativePoliciesReports": {
      "errors": [
        "InvalidParameter"
      ]
    },
    "describeElasticGpus": {
      "errors": [
        "UnsupportedOperation"
      ]
    },
    "describeExportImageTasks": {
      "errors": [
        "InvalidExportTaskID.Malformed"
      ]
    },
    "describeExportTasks": {
      "errors": [
        "InvalidExportTaskID.Malformed"
      ]
    },
    "describeFastLaunchImages": {
      "errors": [
        "InvalidRequest"
      ]
    },
    "describeFleets": {
      "errors": [
        "InvalidFleetId.Malformed"
      ]
    },
    "describeFpgaImages": {
      "errors": [
        "InvalidFpgaImageID.Malformed"
      ]
    },
    "describeHostReservationOfferings": {
      "errors": [
        "InvalidHostReservationOfferingId.Malformed"
      ]
    },
    "describeIamInstanceProfileAssociations": {
      "errors": [
        "InvalidParameterValue"
      ]
    },
    "describeImageReferences": {
      "errors": [
        "InvalidAMIID.Malformed"
      ]
    },
    "describeImageUsageReportEntries": {
      "errors": [
        "InvalidParameterValue"
      ]
    },
    "describeImageUsageReports": {
      "errors": [
        "InvalidParameterValue"
      ]
    },
    "describeImportImageTasks": {
      "errors": [
        "InvalidParameter"
      ]
    },
    "describeImportSnapshotTasks": {
      "errors": [
        "InvalidParameter"
      ]
    },
    "describeInstanceConnectEndpoints": {
      "errors": [
        "InvalidInstanceConnectEndpointId.NotFound"
      ]
    },
    "describeInstanceCreditSpecifications": {
      "errors": [
        "InvalidInstanceID.Malformed"
      ]
    },
    "describeInstanceEventWindows": {
      "errors": [
        "InvalidInstanceEventWindowIDNotFound"
      ]
    },
    "describeInstanceImageMetadata": {
      "errors": [
        "InvalidInstanceID.Malformed"
      ]
    },
    "describeInstanceSqlHaHistoryStates": {
      "errors": [
        "InvalidInstanceID.NotFound"
      ]
    },
    "describeInstanceSqlHaStates": {
      "errors": [
        "InvalidInstanceID.NotFound"
      ]
    },
    "describeIpamExternalResourceVerificationTokens": {
      "errors": [
        "InvalidIpamExternalResourceVerificationTokenId.NotFound"
      ]
    },
    "describeIpamPolicies": {
      "errors": [
        "InvalidIpamPolicyId.NotFound"
      ]
    },
    "describeIpamPools": {
      "errors": [
        "InvalidIpamPoolId.NotFound"
      ]
    },
    "describeIpamPrefixListResolverTargets": {
      "errors": [
        "InvalidIpamPrefixListResolverTargetId.Malformed"
      ]
    },
    "describeIpamPrefixListResolvers": {
      "errors": [
        "InvalidIpamPrefixListResolverId.NotFound"
      ]
    },
    "describeIpamResourceDiscoveries": {
      "errors": [
        "InvalidIpamResourceDiscoveryId.NotFound"
      ]
    },
    "describeIpamResourceDiscoveryAssociations": {
      "errors": [
        "InvalidIpamResourceDiscoveryAssociationId.NotFound"
      ]
    },
    "describeIpamScopes": {
      "errors": [
        "InvalidIpamScopeId.NotFound"
      ]
    },
    "describeIpams": {
      "errors": [
        "InvalidIpamId.NotFound"
      ]
    },
    "describeIpv6Pools": {
      "errors": [
        "InvalidIpv6PoolID.NotFound"
      ]
    },
    "describeLockedSnapshots": {
      "errors": [
        "InvalidRequest"
      ]
    },
    "describeMacHosts": {
      "errors": [
        "InvalidHostID.Malformed"
      ]
    },
    "describeMacModificationTasks": {
      "errors": [
        "InvalidParameter"
      ]
    },
    "describeNetworkInsightsAccessScopeAnalyses": {
      "errors": [
        "InvalidParameterValue"
      ]
    },
    "describeNetworkInsightsAccessScopes": {
      "errors": [
        "InvalidParameterValue"
      ]
    },
    "describeNetworkInsightsAnalyses": {
      "errors": [
        "InvalidParameterValue"
      ]
    },
    "describeNetworkInsightsPaths": {
      "errors": [
        "InvalidParameterValue"
      ]
    },
    "describeNetworkInterfacePermissions": {
      "errors": [
        "InvalidPermissionID.NotFound"
      ]
    },
    "describeOutpostLags": {
      "errors": [
        "InvalidOutpostLagID.Malformed"
      ]
    },
    "describePrefixLists": {
      "errors": [
        "InvalidPrefixListId.NotFound"
      ]
    },
    "describePublicIpv4Pools": {
      "errors": [
        "InvalidPublicIpv4PoolID.NotFound"
      ]
    },
    "describeReplaceRootVolumeTasks": {
      "errors": [
        "InvalidParameterValue"
      ]
    },
    "describeReservedInstances": {
      "errors": [
        "InvalidParameterValue"
      ]
    },
    "describeReservedInstancesModifications": {
      "errors": [
        "InvalidParameterValue"
      ]
    },
    "describeReservedInstancesOfferings": {
      "errors": [
        "InvalidParameterValue"
      ]
    },
    "describeRouteServerEndpoints": {
      "errors": [
        "InvalidRouteServerEndpointId.NotFound"
      ]
    },
    "describeRouteServerPeers": {
      "errors": [
        "InvalidRouteServerPeerId.NotFound"
      ]
    },
    "describeRouteServers": {
      "errors": [
        "InvalidRouteServerId.NotFound"
      ]
    },
    "describeServiceLinkVirtualInterfaces": {
      "errors": [
        "InvalidServiceLinkVirtualInterfaceID.Malformed"
      ]
    },
    "describeTrafficMirrorFilters": {
      "errors": [
        "InvalidTrafficMirrorFilterId.NotFound"
      ]
    },
    "describeTrafficMirrorSessions": {
      "errors": [
        "InvalidTrafficMirrorSessionId.NotFound"
      ]
    },
    "describeTrafficMirrorTargets": {
      "errors": [
        "InvalidTrafficMirrorTargetId.NotFound"
      ]
    },
    "describeTransitGatewayConnectPeers": {
      "errors": [
        "InvalidTransitGatewayConnectPeerID.NotFound"
      ]
    },
    "describeTransitGatewayConnects": {
      "errors": [
        "InvalidTransitGatewayAttachmentID.NotFound"
      ]
    },
    "describeTransitGatewayMeteringPolicies": {
      "errors": [
        "InvalidTransitGatewayMeteringPolicyId.NotFound"
      ]
    },
    "describeTransitGatewayMulticastDomains": {
      "errors": [
        "InvalidTransitGatewayMulticastDomainId.NotFound"
      ]
    },
    "describeTransitGatewayPeeringAttachments": {
      "errors": [
        "InvalidTransitGatewayAttachmentID.NotFound"
      ]
    },
    "describeTransitGatewayPolicyTables": {
      "errors": [
        "InvalidTransitGatewayPolicyTableId.NotFound"
      ]
    },
    "describeTransitGatewayRouteTableAnnouncements": {
      "errors": [
        "InvalidTransitGatewayRouteTableAnnouncementId.Malformed"
      ]
    },
    "describeTransitGatewayVpcAttachments": {
      "errors": [
        "InvalidTransitGatewayAttachmentID.NotFound"
      ]
    },
    "describeTrunkInterfaceAssociations": {
      "errors": [
        "OperationNotPermitted"
      ]
    },
    "describeVerifiedAccessEndpoints": {
      "errors": [
        "InvalidParameterCombination"
      ]
    },
    "describeVerifiedAccessGroups": {
      "errors": [
        "InvalidVerifiedAccessGroupId.NotFound"
      ]
    },
    "describeVerifiedAccessInstanceLoggingConfigurations": {
      "errors": [
        "InvalidVerifiedAccessInstanceId.NotFound"
      ]
    },
    "describeVerifiedAccessInstances": {
      "errors": [
        "InvalidVerifiedAccessInstanceId.NotFound"
      ]
    },
    "describeVerifiedAccessTrustProviders": {
      "errors": [
        "InvalidVerifiedAccessTrustProviderId.NotFound"
      ]
    },
    "describeVolumeStatus": {
      "errors": [
        "InvalidVolumeID.Malformed"
      ]
    },
    "describeVolumesModifications": {
      "errors": [
        "InvalidVolumeID.Malformed"
      ]
    },
    "describeVpcEncryptionControls": {
      "errors": [
        "InvalidParameterCombination"
      ]
    },
    "describeVpcEndpointConnectionNotifications": {
      "errors": [
        "InvalidConnectionNotification"
      ]
    },
    "describeVpnConcentrators": {
      "errors": [
        "InvalidVpnConcentratorId.Malformed"
      ]
    },
    "disableFastSnapshotRestores": {
      "errors": [
        "MissingParameter"
      ]
    },
    "disableInstanceSqlHaStandbyDetections": {
      "errors": [
        "InvalidInstanceID.Malformed"
      ]
    },
    "enableFastSnapshotRestores": {
      "errors": [
        "MissingParameter"
      ]
    },
    "enableInstanceSqlHaStandbyDetections": {
      "errors": [
        "InvalidInstanceID.Malformed"
      ]
    },
    "getReservedInstancesExchangeQuote": {
      "errors": [
        "InvalidReservedInstancesID.NotFound"
      ]
    },
    "listImagesInRecycleBin": {
      "errors": [
        "InvalidAMIID.NotFound"
      ]
    },
    "listSnapshotsInRecycleBin": {
      "errors": [
        "InvalidSnapshotID.Malformed"
      ]
    },
    "listVolumesInRecycleBin": {
      "errors": [
        "InvalidVolumeID.Malformed"
      ]
    },
    "modifyReservedInstances": {
      "errors": [
        "InvalidParameterValue"
      ]
    },
    "cancelConversionTask": {
      "errors": [
        "InvalidAction"
      ]
    },
    "describeCapacityBlockOfferings": {
      "errors": [
        "InvalidParameterValue"
      ]
    },
    "describeClientVpnAuthorizationRules": {
      "errors": [
        "InvalidClientVpnEndpointId.NotFound"
      ]
    },
    "describeMovingAddresses": {
      "errors": [
        "UnsupportedOperation"
      ]
    },
    "associateInstanceEventWindow": {
      "errors": [
        "MissingParameter"
      ]
    },
    "associateIpamByoasn": {
      "errors": [
        "InvalidCidr.NotFound"
      ]
    },
    "authorizeClientVpnIngress": {
      "errors": [
        "MissingParameter"
      ]
    },
    "createCapacityReservationFleet": {
      "errors": [
        "MissingParameter"
      ]
    },
    "createFleet": {
      "errors": [
        "MissingParameter"
      ]
    },
    "createFpgaImage": {
      "errors": [
        "InvalidParameterValue"
      ]
    },
    "createInstanceEventWindow": {
      "errors": [
        "InvalidParameterValue"
      ]
    },
    "createRestoreImageTask": {
      "errors": [
        "InvalidRequest"
      ]
    },
    "createSnapshots": {
      "errors": [
        "MissingParameter"
      ]
    },
    "acceptTransitGatewayMulticastDomainAssociations": {
      "errors": [
        "MissingParameter"
      ]
    },
    "advertiseByoipCidr": {
      "errors": [
        "RequestLimitExceeded"
      ]
    },
    "disableAwsNetworkPerformanceMetricSubscription": {
      "errors": [
        "MissingParameter"
      ]
    },
    "disableCapacityManager": {
      "errors": [
        "CapacityManager.Disabled"
      ]
    },
    "disableIpamOrganizationAdminAccount": {
      "errors": [
        "InvalidParameterValue"
      ]
    },
    "enableAwsNetworkPerformanceMetricSubscription": {
      "errors": [
        "MissingParameter"
      ]
    },
    "enableIpamOrganizationAdminAccount": {
      "errors": [
        "InvalidParameterValue"
      ]
    },
    "enableSnapshotBlockPublicAccess": {
      "errors": [
        "MissingParameter"
      ]
    },
    "modifyClientVpnEndpoint": {
      "errors": [
        "InvalidClientVpnEndpointId.NotFound"
      ]
    },
    "modifyDefaultCreditSpecification": {
      "errors": [
        "MissingParameter"
      ]
    },
    "modifyEbsDefaultKmsKeyId": {
      "errors": [
        "InvalidParameterValue"
      ]
    },
    "modifyInstanceMetadataDefaults": {
      "errors": [
        "MissingParameter"
      ]
    },
    "modifyInstanceNetworkPerformanceOptions": {
      "errors": [
        "InvalidAction"
      ]
    },
    "modifyLaunchTemplate": {
      "errors": [
        "MissingParameter"
      ]
    },
    "exportClientVpnClientCertificateRevocationList": {
      "errors": [
        "InvalidClientVpnEndpointId.NotFound"
      ]
    },
    "exportClientVpnClientConfiguration": {
      "errors": [
        "InvalidClientVpnEndpointId.NotFound"
      ]
    },
    "requestSpotFleet": {
      "errors": [
        "MissingParameter"
      ]
    },
    "createVpcEndpointServiceConfiguration": {
      "errors": [
        "InvalidParameter"
      ]
    },
    "createVpnConcentrator": {
      "errors": [
        "MissingParameter"
      ]
    },
    "describeSpotFleetInstances": {
      "errors": [
        "InvalidParameterValue"
      ]
    },
    "describeSpotFleetRequestHistory": {
      "errors": [
        "MissingParameter"
      ]
    },
    "getAwsNetworkPerformanceData": {
      "errors": [
        "MissingParameter"
      ]
    },
    "getCapacityManagerMetricData": {
      "errors": [
        "MissingParameter"
      ]
    },
    "getCapacityManagerMetricDimensions": {
      "errors": [
        "MissingParameter"
      ]
    },
    "getDefaultCreditSpecification": {
      "errors": [
        "MissingParameter"
      ]
    },
    "getInstanceTypesFromInstanceRequirements": {
      "errors": [
        "MissingParameter"
      ]
    },
    "importClientVpnClientCertificateRevocationList": {
      "errors": [
        "InvalidClientVpnEndpointId.NotFound"
      ]
    },
    "importImage": {
      "errors": [
        "MissingRequiredParameter"
      ]
    },
    "importInstance": {
      "errors": [
        "InvalidParameter"
      ]
    },
    "importSnapshot": {
      "errors": [
        "InvalidParameter"
      ]
    },
    "modifySpotFleetRequest": {
      "errors": [
        "InvalidParameterValue"
      ]
    },
    "moveAddressToVpc": {
      "errors": [
        "UnsupportedOperation"
      ]
    },
    "provisionByoipCidr": {
      "errors": [
        "InvalidParameterValue"
      ]
    },
    "purchaseReservedInstancesOffering": {
      "errors": [
        "InvalidParameterValue"
      ]
    },
    "purchaseScheduledInstances": {
      "errors": [
        "InvalidPurchaseToken.Malformed"
      ]
    },
    "registerInstanceEventNotificationAttributes": {
      "errors": [
        "MissingParameter"
      ]
    },
    "restoreAddressToClassic": {
      "errors": [
        "UnsupportedOperation"
      ]
    },
    "revokeClientVpnIngress": {
      "errors": [
        "MissingParameter"
      ]
    },
    "updateCapacityManagerOrganizationsAccess": {
      "errors": [
        "MissingParameter"
      ]
    },
    "updateSecurityGroupRuleDescriptionsEgress": {
      "errors": [
        "MissingParameter"
      ]
    },
    "updateSecurityGroupRuleDescriptionsIngress": {
      "errors": [
        "MissingParameter"
      ]
    }
  },
  "enums": {
    "InstanceType": {
      "add": [
        "c8gb.12xlarge",
        "c8gb.16xlarge",
        "c8gb.24xlarge",
        "c8gb.2xlarge",
        "c8gb.4xlarge",
        "c8gb.8xlarge",
        "c8gb.large",
        "c8gb.medium",
        "c8gb.metal-24xl",
        "c8gb.xlarge",
        "m8gb.12xlarge",
        "m8gb.16xlarge",
        "m8gb.24xlarge",
        "m8gb.2xlarge",
        "m8gb.4xlarge",
        "m8gb.8xlarge",
        "m8gb.large",
        "m8gb.medium",
        "m8gb.xlarge",
        "m8gn.12xlarge",
        "m8gn.16xlarge",
        "m8gn.24xlarge",
        "m8gn.2xlarge",
        "m8gn.48xlarge",
        "m8gn.4xlarge",
        "m8gn.8xlarge",
        "m8gn.large",
        "m8gn.medium",
        "m8gn.xlarge"
      ]
    },
    "RIProductDescription": {
      "add": [
        "Red Hat Enterprise Linux",
        "SUSE Linux",
        "Ubuntu Pro Linux"
      ]
    },
    "HypervisorType": {
      "add": [
        "nitro"
      ]
    },
    "VirtualizationType": {
      "add": [
        "nested-virtualization"
      ]
    }
  }
}